geopandas_ai-0.0.35.dist-info/licenses/LICENSE.MD
geopandasai/__init__.py
geopandasai/config.py
geopandasai/geodataframe_ai.py
geopandasai/wrapper.py
geopandasai/external/__init__.py
geopandasai/external/cache/__init__.py
geopandasai/external/cache/utils.py
geopandasai/external/cache/backend/__init__.py
geopandasai/external/cache/backend/base.py
geopandasai/external/cache/backend/file_system.py
geopandasai/external/cache/backend/in_memory.py
geopandasai/services/__init__.py
geopandasai/services/code/__init__.py
geopandasai/services/code/code.py
geopandasai/services/code/template.py
geopandasai/services/code/_internal/__init__.py
geopandasai/services/code/_internal/code.py
geopandasai/services/code/_internal/determine_type.py
geopandasai/services/code/_internal/execute.py
geopandasai/services/code/_internal/magic.py
geopandasai/services/code/_internal/memory.py
geopandasai/services/code/_internal/samples.py
geopandasai/services/code/executor/__init__.py
geopandasai/services/code/executor/base.py
geopandasai/services/code/executor/trusted.py
geopandasai/services/code/executor/untrusted.py
geopandasai/services/code/templates/code.json
geopandasai/services/code/templates/code_previously_error.json
geopandasai/services/code/templates/determine_type.json
geopandasai/services/description/__init__.py
geopandasai/services/description/describe.py
geopandasai/services/description/descriptor/__init__.py
geopandasai/services/description/descriptor/base.py
geopandasai/services/description/descriptor/public.py
geopandasai/services/inject/__init__.py
geopandasai/services/inject/inject.py
geopandasai/services/inject/regex.py
geopandasai/services/inject/injectors/__init__.py
geopandasai/services/inject/injectors/base.py
geopandasai/services/inject/injectors/factory.py
geopandasai/services/inject/injectors/jupyter_inject.py
geopandasai/services/inject/injectors/print_inject.py
geopandasai/services/inject/injectors/python_inject.py
geopandasai/shared/__init__.py
geopandasai/shared/constants.py
geopandasai/shared/return_type.py
geopandas_ai-0.0.35.dist-info/METADATA
geopandas_ai-0.0.35.dist-info/WHEEL
geopandas_ai-0.0.35.dist-info/top_level.txt
geopandas_ai-0.0.35.dist-info/RECORD
