Metadata-Version: 2.4
Name: geopandas-ai
Version: 0.0.35
Summary: GeoPandas AI is an extension of GeoPandas allowing you to interact with your spatial data in natural language.
Author-email: Gaspard Merten <gaspard@norse.be>, Mahmoud Sakr <mahmoud.sakr@ulb.be>, Gilles Dejaegere <gilles.dejaegere@ulb.be>
Maintainer-email: Gaspard Merten <gaspard@norse.be>
License-Expression: MIT
Project-URL: Homepage, https://geopandas.ai
Project-URL: Repository, https://github.com/GeoPandas-AI/geopandas-ai.git
Project-URL: Bug Tracker, https://github.com/GeoPandas-AI/geopandas-ai/issues
Keywords: geopandas,geospatial,spatial data,natural language processing,nlp,ai,artificial intelligence,machine learning,data science,python,gis,geographic information systems
Classifier: Programming Language :: Python :: 3
Classifier: Operating System :: OS Independent
Requires-Python: >=3.8
License-File: LICENSE.MD
Requires-Dist: geopandas
Requires-Dist: folium
Requires-Dist: matplotlib
Requires-Dist: litellm
Requires-Dist: ipynbname
Requires-Dist: colorama
Requires-Dist: contextily
Requires-Dist: dependency-injector
Dynamic: license-file
